passmate/__init__.py
passmate/busy_spinner.py
passmate/cli.py
passmate/config.py
passmate/confirm_yes_no.py
passmate/container.py
passmate/generate.py
passmate/migrate_v1.py
passmate/pathtree.py
passmate/raw_db.py
passmate/read_passphrase.py
passmate/session.py
passmate/shell.py
passmate-0.3.dist-info/entry_points.txt
passmate-0.3.dist-info/licenses/LICENSE
passmate-0.3.dist-info/WHEEL
passmate-0.3.dist-info/METADATA
passmate-0.3.dist-info/RECORD
