Metadata-Version: 2.4
Name: passmate
Version: 0.3
Summary: A simple password manager with synchronization
Author-email: Tobias Kaiser <mail@tb-kaiser.de>
Requires-Python: >=3.7
Classifier: License :: OSI Approved :: Apache Software License
License-File: LICENSE
Requires-Dist: scrypt >=0.8.6
Requires-Dist: prompt-toolkit >=3.0.9
Requires-Dist: toml >=0.10.0
Requires-Dist: jsonschema >=3.2.0
Project-URL: Source, https://github.com/TobiasKaiser/passmate
